README.rst
setup.cfg
setup.py
tests/__init__.py
tests/test_voyeur.py
voyeur/__init__.py
voyeur/types.py
voyeur.egg-info/PKG-INFO
voyeur.egg-info/SOURCES.txt
voyeur.egg-info/dependency_links.txt
voyeur.egg-info/top_level.txt