Metadata-Version: 1.0
Name: voyeur
Version: 0.1.1
Summary: Dead simple library for object serialization
Home-page: https://github.com/gilles/voyeur
Author: Gilles Devaux
Author-email: gilles.devaux@gmail.com
License: MIT
Platform: UNKNOWN
